ez_markdown_parser/__init__.py
ez_markdown_parser/main.py
ez_markdown_parser-0.0.3.dist-info/METADATA
ez_markdown_parser-0.0.3.dist-info/WHEEL
ez_markdown_parser-0.0.3.dist-info/top_level.txt
ez_markdown_parser-0.0.3.dist-info/RECORD
