Metadata-Version: 2.1
Name: ez-markdown-parser
Version: 0.0.3
